{"tid":1447691,"cid":5,"subCid":0,"title":"轉發真相運動 [求置頂]","createTime":"2019-08-11T16:07:59.000Z","updateTime":"2019-08-11T16:21:49.000Z","uid":304341,"like":5,"dislike":0,"uniUserReply":5,"replies":[{"pid":"ddf1c267c8025f0d6dbf15a669108613d88251ad","tid":1447691,"uid":304341,"like":0,"dislike":0,"score":0,"citedBy":0,"replyTime":"2019-08-11T16:07:59.000Z","msg":"現發起whatsapp/facebook轉發真相運動 <br />\n麻煩請將下列真相轉發予所有有良知的朋友🙇🏻&zwj;♂️🙇🏻&zwj;♂️🙇🏻&zwj;♂️<br />\n<br />\n本人已發予超過二十位朋友 希望一轉十 十轉百 令全港的所有市民知道真相<br />\n<br />\n感謝各位仍未放棄香港的人<br />\n<br />\n<br />\n<img src=\"https://na.cx/i/x7y21pG.jpg\" data-thumbnail-src=\"https://i.lih.kg/thumbnail?u=https%3A%2F%2Fna.cx%2Fi%2Fx7y21pG.jpg&h=6bad5a43&s={SIZE}\" /><img src=\"https://na.cx/i/9v4Rah2.jpg\" data-thumbnail-src=\"https://i.lih.kg/thumbnail?u=https%3A%2F%2Fna.cx%2Fi%2F9v4Rah2.jpg&h=63a4dd19&s={SIZE}\" /><img src=\"https://na.cx/i/sFgHgX2.jpg\" data-thumbnail-src=\"https://i.lih.kg/thumbnail?u=https%3A%2F%2Fna.cx%2Fi%2FsFgHgX2.jpg&h=d3c0b97a&s={SIZE}\" /><img src=\"https://na.cx/i/L9jUSwo.jpg\" data-thumbnail-src=\"https://i.lih.kg/thumbnail?u=https%3A%2F%2Fna.cx%2Fi%2FL9jUSwo.jpg&h=bab8e18c&s={SIZE}\" /><img src=\"https://na.cx/i/QX99GpK.jpg\" data-thumbnail-src=\"https://i.lih.kg/thumbnail?u=https%3A%2F%2Fna.cx%2Fi%2FQX99GpK.jpg&h=9ea60294&s={SIZE}\" /><img src=\"https://na.cx/i/RxLMJC4.jpg\" data-thumbnail-src=\"https://i.lih.kg/thumbnail?u=https%3A%2F%2Fna.cx%2Fi%2FRxLMJC4.jpg&h=34994fb4&s={SIZE}\" /><img src=\"https://na.cx/i/hVwPGpL.jpg\" data-thumbnail-src=\"https://i.lih.kg/thumbnail?u=https%3A%2F%2Fna.cx%2Fi%2FhVwPGpL.jpg&h=99ce709a&s={SIZE}\" />"},{"pid":"438192f6ba126a4fd5f2532a69069496f5beb096","tid":1447691,"uid":304341,"like":0,"dislike":0,"score":0,"citedBy":0,"replyTime":"2019-08-11T16:08:24.000Z","msg":"自推1"},{"pid":"e3186cf65f53793d2fcbfcde8d1142ca99319a39","tid":1447691,"uid":304341,"like":0,"dislike":0,"score":0,"citedBy":0,"replyTime":"2019-08-11T16:08:36.000Z","msg":"自推2"},{"pid":"b003e8ebdfe4db06685bd5558fa8b01e8a869b6e","tid":1447691,"uid":304341,"like":0,"dislike":0,"score":0,"citedBy":0,"replyTime":"2019-08-11T16:08:49.000Z","msg":"自推3"},{"pid":"e22c6af899ab059917623035d4cd5e875c93ccd4","tid":1447691,"uid":304341,"like":0,"dislike":0,"score":0,"citedBy":0,"replyTime":"2019-08-11T16:09:35.000Z","msg":"自推4"},{"pid":"58703aba3ade1de6b6ba33d6441b3f09652c1d17","tid":1447691,"uid":304341,"like":0,"dislike":0,"score":0,"citedBy":0,"replyTime":"2019-08-11T16:09:46.000Z","msg":"自推5"},{"pid":"dd42c51a3c76d6e7c3aea3ef6c70fe5d0b1c7fe0","tid":1447691,"uid":304341,"like":0,"dislike":0,"score":0,"citedBy":0,"replyTime":"2019-08-11T16:10:01.000Z","msg":"自推6"},{"pid":"beb9f2a84cfe95f135c1cfacc176b1b823f87487","tid":1447691,"uid":304341,"like":0,"dislike":0,"score":0,"citedBy":0,"replyTime":"2019-08-11T16:10:11.000Z","msg":"自推7"},{"pid":"aaa6ae4a2f0f029c7decbe356cee0829a76b7ce6","tid":1447691,"uid":304341,"like":0,"dislike":0,"score":0,"citedBy":0,"replyTime":"2019-08-11T16:10:23.000Z","msg":"自推8"},{"pid":"d3dbdcd92e339f6ddddfd9da10ee3ae99c3b8431","tid":1447691,"uid":304341,"like":0,"dislike":0,"score":0,"citedBy":0,"replyTime":"2019-08-11T16:10:35.000Z","msg":"自推9"},{"pid":"cbd96a29227d0324630bbf5de49c1b7479f4b475","tid":1447691,"uid":304341,"like":0,"dislike":0,"score":0,"citedBy":0,"replyTime":"2019-08-11T16:10:46.000Z","msg":"自推10"},{"pid":"e9e14079e61278a34428367761591260cb4e7e75","tid":1447691,"uid":293281,"like":0,"dislike":0,"score":0,"citedBy":0,"replyTime":"2019-08-11T16:18:21.000Z","msg":"721"},{"pid":"a494ed68577f999b4af948625bc6b47ea3ed938e","tid":1447691,"uid":33543,"like":0,"dislike":0,"score":0,"citedBy":0,"replyTime":"2019-08-11T16:18:53.000Z","msg":"<img src=\"https://na.cx/i/MQZURP7.jpg\" data-thumbnail-src=\"https://i.lih.kg/thumbnail?u=https%3A%2F%2Fna.cx%2Fi%2FMQZURP7.jpg&h=e8ff53ea&s={SIZE}\" /><img src=\"https://na.cx/i/BvexDu8.jpg\" data-thumbnail-src=\"https://i.lih.kg/thumbnail?u=https%3A%2F%2Fna.cx%2Fi%2FBvexDu8.jpg&h=6025e5fb&s={SIZE}\" /><img src=\"https://na.cx/i/cnQpuBP.jpg\" data-thumbnail-src=\"https://i.lih.kg/thumbnail?u=https%3A%2F%2Fna.cx%2Fi%2FcnQpuBP.jpg&h=bdc91acf&s={SIZE}\" /><br />\n<strong><span style=\"color: red;\"><span style=\"font-size: xx-large;\">Product should only be used outdoors. <br />\n<br />\nDo not fire directly at personnel</span></span></strong><br />\n<br />\n<span style=\"font-size: xx-large;\">記者會上話會跟足廠商指引而無必要親身試彈，宜家冇跟指引就有必要親身試啦？</span><br />\n<br />\n間廠叫NonLethal Technology, 有冇人去提醒下間廠再培訓垃圾狗<br />\n<br />\n<a href=\"http://www.nonlethaltechnologies.com/\" data-sr-url=\"https://r.lihkg.com/link?u=http%3A%2F%2Fwww.nonlethaltechnologies.com%2F&d=6RyWY35l7oH3ui7gcEo%2FTBPX6nNrjY8iteK6A9FjwF0%3D&h=75019e65\" target=\"_blank\">http://www.nonlethaltechnologies.com/</a>"},{"pid":"076f482cb5fe251b64c5839f462373ec29a967b6","tid":1447691,"uid":92740,"like":0,"dislike":0,"score":0,"citedBy":0,"replyTime":"2019-08-11T16:19:46.000Z","msg":"<img src=\"https://na.cx/i/hUeE3HS.jpg\" data-thumbnail-src=\"https://i.lih.kg/thumbnail?u=https%3A%2F%2Fna.cx%2Fi%2FhUeE3HS.jpg&h=d4566311&s={SIZE}\" /><br />\n推"},{"pid":"ef85c2aeb83a52d413e5c55a477bea2d2f2d9e03","tid":1447691,"uid":302475,"like":0,"dislike":0,"score":0,"citedBy":0,"replyTime":"2019-08-11T16:21:49.000Z","msg":"係時候將文宣升級<br />\n我寫左篇長建議，麻煩各位推一推<br />\n希望大家睇一睇！！<br />\n<a href=\"https://lihkg.com/thread/1444832/page/1\" data-auto-link target=\"_blank\">https://lihkg.com/thread/1444832/page/1</a>"}]}