{"tid":176182,"cid":4,"subCid":0,"title":"★ios10.3好似fix左keyboard切換符號有時freeze的bug !","createTime":"2017-03-28T04:28:37.000Z","updateTime":"2017-03-28T12:54:34.000Z","uid":19454,"like":1,"dislike":0,"uniUserReply":0,"replies":[{"pid":"ea92d5ea2118e070367b53f314704c5763ea7286","tid":176182,"uid":19454,"like":0,"dislike":0,"score":0,"citedBy":0,"replyTime":"2017-03-28T04:28:37.000Z","msg":"<span style=\"font-size: xx-large;\">好似</span><br />\n<br />\nIn Gay cook , I don't trust<br />\n<br />\n<br />\n<img src=\"/assets/faces/normal/dead.gif\" class=\"hkgmoji\" />"},{"pid":"cda6c2088a0f55d2dc16e104531314494e23563c","tid":176182,"uid":19454,"like":0,"dislike":0,"score":0,"citedBy":0,"replyTime":"2017-03-28T04:29:36.000Z","msg":"Apple 已死，連咁簡單都要fix大半年<img src=\"/assets/faces/lomoji/25.png\" class=\"hkgmoji\" />"},{"pid":"2755b2c8006732a607557ddf3eea947dfef57a35","tid":176182,"uid":19454,"like":0,"dislike":0,"score":0,"citedBy":0,"replyTime":"2017-03-28T04:40:29.000Z","msg":"<img src=\"/assets/faces/normal/fuck.gif\" class=\"hkgmoji\" /> <img src=\"/assets/faces/normal/fuck.gif\" class=\"hkgmoji\" /> <img src=\"/assets/faces/normal/fuck.gif\" class=\"hkgmoji\" /> <img src=\"/assets/faces/normal/fuck.gif\" class=\"hkgmoji\" />"},{"pid":"48d598112e6f56dca70ee8b5b03314ed0d3e0b17","tid":176182,"uid":81113,"like":0,"dislike":0,"score":0,"citedBy":0,"replyTime":"2017-03-28T05:11:45.000Z","msg":"我冇freeze過嘅？<br />\nIp6s+"},{"pid":"b6ee5400c3d7a92303b398797153104cade289de","tid":176182,"uid":19454,"like":0,"dislike":0,"score":0,"citedBy":0,"replyTime":"2017-03-28T05:24:28.000Z","msg":"<blockquote>我冇freeze過嘅？<br />\nIp6s+</blockquote><br />\nipad打橫開才會咁"},{"pid":"37d3df9eace2972e3b2c193f29e0e3b70bbeed5e","tid":176182,"uid":5836,"like":0,"dislike":0,"score":0,"citedBy":0,"replyTime":"2017-03-28T12:54:34.000Z","msg":"6s 即時換到<br />\n之前好似要load一load<img src=\"/assets/faces/normal/shocking.gif\" class=\"hkgmoji\" />"}]}