{"tid":1977893,"cid":34,"subCid":0,"title":"[懷舊] 人人玩新版 堅持玩舊版 Final Fantasy VII (Eng) 18/4 DAY 6","createTime":"2020-04-18T09:51:32.000Z","updateTime":"2020-04-18T13:31:10.000Z","uid":130568,"like":1,"dislike":1,"uniUserReply":2,"replies":[{"pid":"cdfdc5da6ba31936afbc0c118c5aa0097f152837","tid":1977893,"uid":130568,"like":0,"dislike":0,"score":0,"citedBy":0,"replyTime":"2020-04-18T09:51:32.000Z","msg":"<a href=\"https://youtu.be/St9ZkQlnWLA\" data-sr-url=\"https://r.lihkg.com/link?u=https%3A%2F%2Fyoutu.be%2FSt9ZkQlnWLA&d=0xR7vGHOl893LUq1yoppeq0EM2ZTCgB2Df5M2YAuo3Y%3D&h=67805cee\" data-auto-link target=\"_blank\">https://youtu.be/St9ZkQlnWLA</a>"},{"pid":"7f0ff6b962cf8b1347c607631cc8d62080f2d8f5","tid":1977893,"uid":210491,"like":0,"dislike":0,"score":0,"citedBy":0,"replyTime":"2020-04-18T13:31:10.000Z","msg":"<img src=\"/assets/faces/normal/agree.gif\" class=\"hkgmoji\" />"}]}